devops_code_generator_library/__init__.py
devops_code_generator_library/chains/find_middleware/__init__.py
devops_code_generator_library/chains/find_middleware/find_middleware_chain.py
devops_code_generator_library/code_repository.py
devops_code_generator_library/devops_code_generator_base.py
devops_code_generator_library/devops_code_generator_output_parser.py
devops_code_generator_library/git_source_code_repository.py
devops_code_generator_library/repository.py
devops_code_generator_library/source_code_repository.py
devops_code_generator_library/templates/find_middleware/java/apache_maven/middlewares.txt
devops_code_generator_library/templates/find_middleware/python/poetry/middlewares.txt
devops_code_generator_library-1.20240709.3.dist-info/LICENSE
devops_code_generator_library-1.20240709.3.dist-info/METADATA
devops_code_generator_library-1.20240709.3.dist-info/WHEEL
devops_code_generator_library-1.20240709.3.dist-info/RECORD
